{
  "company": {
    "data": "Wonderbly",
    "label": "company"
  },
  "system": {
    "data": "Wonderbly Design System",
    "label": "system",
    "url": "http://design-system.lostmy.name/"
  },
  "repository": {
    "data": "GitHub",
    "label": "repository",
    "url": ""
  },
  "codeDepth": {
    "data": "HTML/CSS/JS",
    "label": "code depth"
  },
  "components": {
    "data": "yes",
    "label": "components"
  },
  "js": {
    "data": "React",
    "label": "JS library/framework"
  },
  "ts": {
    "data": "no",
    "label": "typescript"
  },
  "webComponents": {
    "data": "no",
    "label": "web components"
  },
  "tests": {
    "data": "no data",
    "label": "tests"
  },
  "linter": {
    "data": "no data",
    "label": "linter"
  },
  "css": {
    "data": "no data",
    "label": "CSS"
  },
  "cssInjs": {
    "data": "no data",
    "label": "CSS in JS"
  },
  "designTokens": {
    "data": "no data",
    "label": "design tokens"
  },
  "bundleManager": {
    "data": "no data",
    "label": "bundle manager"
  },
  "uiKit": {
    "data": "no data",
    "label": "UI kit"
  },
  "brandGuidelines": {
    "data": "no data",
    "label": "brand guidelines",
    "url": ""
  },
  "colorPalette": {
    "data": "yes",
    "label": "color palette",
    "url": "http://design-system.lostmy.name/rules/Colour"
  },
  "colorNaming": {
    "data": [
      "natural (e.g. Light Green)",
      "abstract (e.g. stone)"
    ],
    "label": "color naming"
  },
  "contrastAnalysis": {
    "data": "no",
    "label": "contrast analysis",
    "url": ""
  },
  "typography": {
    "data": "no data",
    "label": "typography",
    "url": ""
  },
  "icons": {
    "data": "Icon Font",
    "label": "icons",
    "url": ""
  },
  "space/Grid": {
    "data": "yes",
    "label": "space / grid",
    "url": "http://design-system.lostmy.name/rules/Grid"
  },
  "illustrations": {
    "data": "no",
    "label": "illustration",
    "url": ""
  },
  "dataVisualization": {
    "data": "no",
    "label": "data visualization",
    "url": ""
  },
  "animation": {
    "data": "yes",
    "label": "animation",
    "url": "http://design-system.lostmy.name/components/wrappers/Animation"
  },
  "voiceTone": {
    "data": "no",
    "label": "voice & tone",
    "url": ""
  },
  "accessibilityGuidelines": {
    "data": "no",
    "label": "accessibility guidelines",
    "url": ""
  },
  "designPrinciples": {
    "data": "yes",
    "label": "design principles",
    "url": "http://design-system.lostmy.name/design-principles"
  },
  "websiteDocumentation": {
    "data": "yes",
    "label": "documentation website",
    "url": "http://design-system.lostmy.name/"
  },
  "codeDocumentation": {
    "data": "no data",
    "label": "code documentation",
    "url": ""
  },
  "storybook": {
    "data": "no data",
    "label": "storybook",
    "url": ""
  },
  "distribution": {
    "data": "no data",
    "label": "distribution"
  }
}